{
    "doctor": {
        "idField": "id",
        "references": {
            "facilities_doctors": {
                "idField": "doctor_id",
                "onDelete": "update"
            },
            "examinations": {
                "idField": "doctor_id",
                "onDelete": "restrict"
            }
        }
    },
    "study": {
        "idField": "id",
        "references": {
            "studies_cpts": {
                "idField": "study_id",
                "onDelete": "update"
            },
            "examinations_studies": {
                "idField": "study_id",
                "onDelete": "restrict"
            },
            "templates_studies": {
                "idField": "study_id",
                "onDelete": "update"
            }
        }
    },
    "examinations": {
        "idField": "id",
        "references": {
            "examinations_studies": {
                "idField": "examination_id",
                "onDelete": "update"
            }
        }
    },
    "patient": {
        "idField": "id",
        "references": {
            "examinations": {
                "idField": "patient_id",
                "onDelete": "restrict"
            }
        }
    },
    "facility": {
        "idField": "id",
        "references": {
            "facilities_doctors": {
                "idField": "facility_id",
                "onDelete": "update"
            },
            "examinations": {
                "idField": "facility_id",
                "onDelete": "restrict"
            }
        }
    }
}
